pyutm/__init__.py
pyutm/__version__.py
pyutm/data.py
pyutm/locate.py
pyutm/main.py
pyutm-0.2.1.dist-info/LICENSE
pyutm-0.2.1.dist-info/METADATA
pyutm-0.2.1.dist-info/WHEEL
pyutm-0.2.1.dist-info/top_level.txt
pyutm-0.2.1.dist-info/RECORD
