Metadata-Version: 2.1
Name: pyutm
Version: 0.2.1
Summary: Creates standardized grid references, unique identifiers and UTM coordinates for point data.
Home-page: https://github.com/FREAC/pyutm
Author: Philip Griffith
Author-email: philip.griffith@fsu.edu
License: UNKNOWN
Platform: UNKNOWN
Classifier: Programming Language :: Python :: 2.7
Classifier: Programming Language :: Python :: 3.6
Classifier: License :: OSI Approved :: MIT License
Classifier: Operating System :: OS Independent
Requires-Dist: numpy
Requires-Dist: pandas
Requires-Dist: pyshp
Requires-Dist: pyproj
